half_adder.v
// half adder module adds two binary digits x,y and outputs the sum and the carry.


module half_adder(output sum, output carry, input a, input b);
    // computes the sum = 1 if only one of the input is 1 by xor the inputs.
    xor(sum, a, b);
    // the carry is 1 only if both input is 1.
    and(carry, a, b);
endmodule

full_adder.v

// full adder module adds three binary digits x,y,z and outputs the sum and the carry.

module full_adder(output sum, output carry, input x, input y, input z);
   wire s1, c1, c2;
   // adding x,y using half adder and put the result in s1 , c1 
   half_adder h1(s1, c1, x, y);
   // adding the result of the first addition with the remaining bit z.
   half_adder h2(sum, c2, s1, z);
   // the output carry is true if any of the two carries is true.
   or(carry, c1, c2);
endmodule

mux.v
// 4x1 multiplixer that chooses the output m to be equal toone of the 4 inputs i0,i1,i2,i3 through 2 bit selector s .

module mux (output m, input i0, input i1, input i2, input i3, input[1:0]s);

    // ng is a 2 bit wire that is equal to the reverse of the input selector s.
	wire[1:0]ng  ;
    wire[3:0] newI ;
	not(ng[0], s[0]);

	not(ng[1], s[1]);
	
    // i0 equals i0 only if both selector input s is 0 otherewise i0 equals 0.
    and(newI[0], i0, ng[0], ng[1]);
	// i1 equals i0 only if both selector input s is 0 otherewise i1 equals 0.
    and(newI[1], i1, s[0], ng[1]);
	// i2 equals i0 only if both selector input s is 0 otherewise i2 equals 0.
    and(newI[2], i2, ng[0], s[1]);
	// i3 equals i0 only if both selector input s is 0 otherewise i3 equals 0.
    and(newI[3], i3, s[0], s[1]);
	// The output is true if any of the inputs is true.
    or(m , newI[0],newI[1], newI[2], newI[3]);

endmodule

circuits.v
/*  
    depending on the input selector s the output G will be determined as follows.
    When the selection inputs are 00, G = A+1
    When the selection inputs are 01, G = A+B
    When the selection inputs are 10, G = B-A
    When the selection inputs are 11, G = 1-B
*/

module circuits(output[2:0]G, output carry, input[2:0]A, input[2:0]B, input[1:0]S);

// a wire that holds the output of the first three multiplixers.
wire[2:0]mL ;
// a wire that will hold the left handside of the addition equasion
wire[2:0]lefthandside ;
// a wire that will hold the right handside of the addition equasion
wire[2:0]righthandside;


// wire to hold the output carries of the full adders.
wire[1:0]cf;

reg one = 1;

// ~one
// first three multiplixers to choose  from A and B to pass.
mux mux_1(mL[0], A[0], A[0], A[0], B[0], S);
mux mux_2(mL[1], A[1], A[1], A[1], B[1], S);
mux mux_3(mL[2], A[2], A[2], A[2], B[2], S);


// the next three multiplixers to choose the right handside of the equasion.
mux mux_4(righthandside[0], one, B[0], B[0], one, S);
mux mux_5(righthandside[1], ~one, B[1], B[1], ~one, S);
mux mux_6(righthandside[2], ~one, B[2], B[2], ~one, S);


// flipping the lefthandside if s1 is true using Xor.
xor (lefthandside[0], S[1], mL[0]);
xor(lefthandside[1], S[1], mL[1]);
xor(lefthandside[2], S[1], mL[2]);

// adding both operands with the cin input as the s1 selector using 3 full adders and the output to be in G and the carry.
full_adder fullAdder_1(G[0], cf[0], S[1], lefthandside[0], righthandside[0]);
full_adder fullAdder_2(G[1], cf[1], cf[0], lefthandside[1], righthandside[1]);
full_adder fullAdder_3(G[2], carry, cf[1], lefthandside[2], righthandside[2]);

endmodule

test_circuits.v
`timescale 1ns / 1ns

module test_circuits;

  reg [2:0] A, B;
  reg [1:0] S;
  wire [2:0] G;
  wire carry;

  // Instantiate the circuits module
  circuits uut (
    .G(G),
    .carry(carry),
    .A(A),
    .B(B),
    .S(S)
  );

  // Stimulus generation
  initial begin
    $display("test started");
    $dumpfile("test_circuits.vcd");
    $dumpvars(0, test_circuits);

    for (integer i = 0; i < 256; i = i +1) begin
        S = i[1:0];
        A = i[4:2];
        B = i[7:5];
        #10;
      $display("Test Case %b: A = %b, B = %b, S = %b, G = %b, carry = %b", i, A, B, S, G, carry);
    end

    // Display the results
    $finish; // End simulation
  end

endmodule

test_circuits.vcd
$date
	Tue Dec 12 22:27:46 2023
$end
$version
	Icarus Verilog
$end
$timescale
	1ns
$end
$scope module test_circuits $end
$var wire 1 ! carry $end
$var wire 3 " G [2:0] $end
$var reg 3 # A [2:0] $end
$var reg 3 $ B [2:0] $end
$var reg 2 % S [1:0] $end
$scope module uut $end
$var wire 3 & A [2:0] $end
$var wire 3 ' B [2:0] $end
$var wire 2 ( S [1:0] $end
$var wire 3 ) righthandside [2:0] $end
$var wire 3 * mL [2:0] $end
$var wire 3 + lefthandside [2:0] $end
$var wire 2 , cf [1:0] $end
$var wire 1 ! carry $end
$var wire 3 - G [2:0] $end
$var reg 1 . one $end
$scope module fullAdder_1 $end
$var wire 1 / carry $end
$var wire 1 0 x $end
$var wire 1 1 y $end
$var wire 1 2 z $end
$var wire 1 3 sum $end
$var wire 1 4 s1 $end
$var wire 1 5 c2 $end
$var wire 1 6 c1 $end
$scope module h1 $end
$var wire 1 0 a $end
$var wire 1 1 b $end
$var wire 1 6 carry $end
$var wire 1 4 sum $end
$upscope $end
$scope module h2 $end
$var wire 1 4 a $end
$var wire 1 2 b $end
$var wire 1 5 carry $end
$var wire 1 3 sum $end
$upscope $end
$upscope $end
$scope module fullAdder_2 $end
$var wire 1 7 carry $end
$var wire 1 8 x $end
$var wire 1 9 y $end
$var wire 1 : z $end
$var wire 1 ; sum $end
$var wire 1 < s1 $end
$var wire 1 = c2 $end
$var wire 1 > c1 $end
$scope module h1 $end
$var wire 1 8 a $end
$var wire 1 9 b $end
$var wire 1 > carry $end
$var wire 1 < sum $end
$upscope $end
$scope module h2 $end
$var wire 1 < a $end
$var wire 1 : b $end
$var wire 1 = carry $end
$var wire 1 ; sum $end
$upscope $end
$upscope $end
$scope module fullAdder_3 $end
$var wire 1 ! carry $end
$var wire 1 ? x $end
$var wire 1 @ y $end
$var wire 1 A z $end
$var wire 1 B sum $end
$var wire 1 C s1 $end
$var wire 1 D c2 $end
$var wire 1 E c1 $end
$scope module h1 $end
$var wire 1 ? a $end
$var wire 1 @ b $end
$var wire 1 E carry $end
$var wire 1 C sum $end
$upscope $end
$scope module h2 $end
$var wire 1 C a $end
$var wire 1 A b $end
$var wire 1 D carry $end
$var wire 1 B sum $end
$upscope $end
$upscope $end
$scope module mux_1 $end
$var wire 1 F i0 $end
$var wire 1 G i1 $end
$var wire 1 H i2 $end
$var wire 1 I i3 $end
$var wire 1 J m $end
$var wire 2 K s [1:0] $end
$var wire 2 L ng [1:0] $end
$var wire 4 M newI [3:0] $end
$upscope $end
$scope module mux_2 $end
$var wire 1 N i0 $end
$var wire 1 O i1 $end
$var wire 1 P i2 $end
$var wire 1 Q i3 $end
$var wire 1 R m $end
$var wire 2 S s [1:0] $end
$var wire 2 T ng [1:0] $end
$var wire 4 U newI [3:0] $end
$upscope $end
$scope module mux_3 $end
$var wire 1 V i0 $end
$var wire 1 W i1 $end
$var wire 1 X i2 $end
$var wire 1 Y i3 $end
$var wire 1 Z m $end
$var wire 2 [ s [1:0] $end
$var wire 2 \ ng [1:0] $end
$var wire 4 ] newI [3:0] $end
$upscope $end
$scope module mux_4 $end
$var wire 1 . i0 $end
$var wire 1 ^ i1 $end
$var wire 1 _ i2 $end
$var wire 1 . i3 $end
$var wire 1 ` m $end
$var wire 2 a s [1:0] $end
$var wire 2 b ng [1:0] $end
$var wire 4 c newI [3:0] $end
$upscope $end
$scope module mux_5 $end
$var wire 1 d i0 $end
$var wire 1 e i1 $end
$var wire 1 f i2 $end
$var wire 1 g i3 $end
$var wire 1 h m $end
$var wire 2 i s [1:0] $end
$var wire 2 j ng [1:0] $end
$var wire 4 k newI [3:0] $end
$upscope $end
$scope module mux_6 $end
$var wire 1 l i0 $end
$var wire 1 m i1 $end
$var wire 1 n i2 $end
$var wire 1 o i3 $end
$var wire 1 p m $end
$var wire 2 q s [1:0] $end
$var wire 2 r ng [1:0] $end
$var wire 4 s newI [3:0] $end
$upscope $end
$upscope $end
$scope begin $ivl_for_loop0 $end
$var integer 32 t i [31:0] $end
$upscope $end
$upscope $end
$enddefinitions $end
$comment Show the parameter values. $end
$dumpall
$end
#0
$dumpvars
b0 t
b0 s
b11 r
b0 q
0p
0o
0n
0m
0l
b0 k
b11 j
b0 i
0h
0g
0f
0e
0d
b1 c
b11 b
b0 a
1`
0_
0^
b0 ]
b11 \
b0 [
0Z
0Y
0X
0W
0V
b0 U
b11 T
b0 S
0R
0Q
0P
0O
0N
b0 M
b11 L
b0 K
0J
0I
0H
0G
0F
0E
0D
0C
0B
0A
0@
0?
0>
0=
0<
0;
0:
09
08
07
06
05
04
13
12
01
00
0/
1.
b1 -
b0 ,
b0 +
b0 *
b1 )
b0 (
b0 '
b0 &
b0 %
b0 $
b0 #
b1 "
0!
$end
#10
b0 "
b0 -
03
02
b0 )
0`
b0 c
b10 L
b10 T
b10 \
b10 b
b10 j
b10 r
b1 %
b1 (
b1 K
b1 S
b1 [
b1 a
b1 i
b1 q
b1 t
#20
1!
1E
1?
17
1>
18
b11 ,
1/
0;
0B
16
0<
0C
11
19
1@
b0 "
b0 -
03
b111 +
04
b1 L
b1 T
b1 \
b1 b
b1 j
b1 r
10
b10 %
b10 (
b10 K
b10 S
b10 [
b10 a
b10 i
b10 q
b10 t
#30
b1 "
b1 -
13
12
b1 )
1`
b0 L
b0 T
b0 \
b0 b
b1000 c
b0 j
b0 r
b11 %
b11 (
b11 K
b11 S
b11 [
b11 a
b11 i
b11 q
b11 t
#40
1;
0?
1<
b1 *
1J
07
0B
0!
12
0>
0C
0E
18
b1 M
b1 )
1`
11
09
0@
b10 "
b10 -
03
15
b1 ,
1/
b1 +
14
06
b11 L
b11 T
b11 \
b11 b
b1 c
b11 j
b11 r
1F
1G
1H
00
b1 #
b1 &
b0 %
b0 (
b0 K
b0 S
b0 [
b0 a
b0 i
b0 q
b100 t
#50
0;
0<
08
b0 ,
0/
b1 "
b1 -
13
05
02
b0 )
0`
b0 c
b10 L
b10 M
b10 T
b10 \
b10 b
b10 j
b10 r
b1 %
b1 (
b1 K
b1 S
b1 [
b1 a
b1 i
b1 q
b101 t
#60
1;
0!
1<
0E
0?
07
1B
0>
1C
08
b1 *
1J
01
19
1@
b111 "
b111 -
13
b0 ,
0/
b110 +
14
06
b1 L
b100 M
b1 T
b1 \
b1 b
b1 j
b1 r
10
b10 %
b10 (
b10 K
b10 S
b10 [
b10 a
b10 i
b10 q
b110 t
#70
0B
1!
0C
1E
1?
04
16
0;
17
11
0<
1>
b111 +
18
b11 ,
1/
b0 *
0J
b1 "
b1 -
13
05
12
b0 M
b1 )
1`
b0 L
b0 T
b0 \
b0 b
b1000 c
b0 j
b0 r
b11 %
b11 (
b11 K
b11 S
b11 [
b11 a
b11 i
b11 q
b111 t
#80
1;
0?
1<
b10 *
1R
07
0B
0!
12
0>
0C
0E
08
b1 U
b1 )
1`
01
19
0@
b11 "
b11 -
13
05
b0 ,
0/
b10 +
04
06
b11 L
b11 T
b11 \
b11 b
b1 c
b11 j
b11 r
0F
0G
0H
1N
1O
1P
00
b10 #
b10 &
b0 %
b0 (
b0 K
b0 S
b0 [
b0 a
b0 i
b0 q
b1000 t
#90
b10 "
b10 -
03
02
b0 )
0`
b0 c
b10 L
b10 T
b10 U
b10 \
b10 b
b10 j
b10 r
b1 %
b1 (
b1 K
b1 S
b1 [
b1 a
b1 i
b1 q
b1001 t
#100
0!
0E
0?
07
0>
18
b1 ,
1/
1;
1B
16
1<
1C
b10 *
1R
11
09
1@
b110 "
b110 -
03
b101 +
04
b1 L
b1 T
b100 U
b1 \
b1 b
b1 j
b1 r
10
b10 %
b10 (
b10 K
b10 S
b10 [
b10 a
b10 i
b10 q
b1010 t
#110
0B
1!
0C
1E
1?
0;
b11 ,
17
0<
1>
19
b111 +
b0 *
0R
b1 "
b1 -
13
12
b0 U
b1 )
1`
b0 L
b0 T
b0 \
b0 b
b1000 c
b0 j
b0 r
b11 %
b11 (
b11 K
b11 S
b11 [
b11 a
b11 i
b11 q
b1011 t
#120
0;
1?
0<
1J
b11 *
1R
17
1B
0!
12
1>
1C
0E
18
b1 M
b1 U
b1 )
1`
11
19
0@
b100 "
b100 -
03
15
b11 ,
1/
b11 +
14
06
b11 L
b11 T
b11 \
b11 b
b1 c
b11 j
b11 r
1F
1G
1H
00
b11 #
b11 &
b0 %
b0 (
b0 K
b0 S
b0 [
b0 a
b0 i
b0 q
b1100 t
#130
0B
0C
0?
1;
07
1<
0>
08
b0 ,
0/
b11 "
b11 -
13
05
02
b0 )
0`
b0 c
b10 L
b10 M
b10 T
b10 U
b10 \
b10 b
b10 j
b10 r
b1 %
b1 (
b1 K
b1 S
b1 [
b1 a
b1 i
b1 q
b1101 t
#140
0;
0<
1B
1C
08
1J
b11 *
1R
01
09
1@
b101 "
b101 -
13
b0 ,
0/
b100 +
14
06
b1 L
b100 M
b1 T
b100 U
b1 \
b1 b
b1 j
b1 r
10
b10 %
b10 (
b10 K
b10 S
b10 [
b10 a
b10 i
b10 q
b1110 t
#150
0B
1!
0C
1E
1?
17
04
16
1>
0;
11
19
0<
b111 +
18
b11 ,
1/
0J
b0 *
0R
b1 "
b1 -
13
05
12
b0 M
b0 U
b1 )
1`
b0 L
b0 T
b0 \
b0 b
b1000 c
b0 j
b0 r
b11 %
b11 (
b11 K
b11 S
b11 [
b11 a
b11 i
b11 q
b1111 t
#160
0;
0?
0<
b100 *
1Z
07
1B
0!
12
0>
1C
0E
08
b1 ]
b1 )
1`
01
09
1@
b101 "
b101 -
13
05
b0 ,
0/
b100 +
04
06
b11 L
b11 T
b11 \
b11 b
b1 c
b11 j
b11 r
0F
0G
0H
0N
0O
0P
1V
1W
1X
00
b100 #
b100 &
b0 %
b0 (
b0 K
b0 S
b0 [
b0 a
b0 i
b0 q
b10000 t
#170
b100 "
b100 -
03
02
b0 )
0`
b0 c
b10 L
b10 T
b10 \
b10 ]
b10 b
b10 j
b10 r
b1 %
b1 (
b1 K
b1 S
b1 [
b1 a
b1 i
b1 q
b10001 t
#180
1?
17
1>
18
b11 ,
1/
0;
1B
16
0<
1C
b100 *
1Z
11
19
0@
b100 "
b100 -
03
b11 +
04
b1 L
b1 T
b1 \
b100 ]
b1 b
b1 j
b1 r
10
b10 %
b10 (
b10 K
b10 S
b10 [
b10 a
b10 i
b10 q
b10010 t
#190
0B
1!
0C
1E
1@
b111 +
b0 *
0Z
b1 "
b1 -
13
12
b0 ]
b1 )
1`
b0 L
b0 T
b0 \
b0 b
b1000 c
b0 j
b0 r
b11 %
b11 (
b11 K
b11 S
b11 [
b11 a
b11 i
b11 q
b10011 t
#200
1;
0?
1<
1J
b101 *
1Z
07
1B
0!
12
0>
1C
0E
18
b1 M
b1 ]
b1 )
1`
11
09
1@
b110 "
b110 -
03
15
b1 ,
1/
b101 +
14
06
b11 L
b11 T
b11 \
b11 b
b1 c
b11 j
b11 r
1F
1G
1H
00
b101 #
b101 &
b0 %
b0 (
b0 K
b0 S
b0 [
b0 a
b0 i
b0 q
b10100 t
#210
0;
0<
08
b0 ,
0/
b101 "
b101 -
13
05
02
b0 )
0`
b0 c
b10 L
b10 M
b10 T
b10 \
b10 ]
b10 b
b10 j
b10 r
b1 %
b1 (
b1 K
b1 S
b1 [
b1 a
b1 i
b1 q
b10101 t
#220
1;
0!
1<
0E
0?
07
0B
0>
0C
08
1J
b101 *
1Z
01
19
0@
b11 "
b11 -
13
b0 ,
0/
b10 +
14
06
b1 L
b100 M
b1 T
b1 \
b100 ]
b1 b
b1 j
b1 r
10
b10 %
b10 (
b10 K
b10 S
b10 [
b10 a
b10 i
b10 q
b10110 t
#230
1!
1E
0B
1?
04
16
0C
0;
17
11
1@
0<
1>
b111 +
18
b11 ,
1/
0J
b0 *
0Z
b1 "
b1 -
13
05
12
b0 M
b0 ]
b1 )
1`
b0 L
b0 T
b0 \
b0 b
b1000 c
b0 j
b0 r
b11 %
b11 (
b11 K
b11 S
b11 [
b11 a
b11 i
b11 q
b10111 t
#240
1;
0?
1<
1R
b110 *
1Z
07
1B
0!
12
0>
1C
0E
08
b1 U
b1 ]
b1 )
1`
01
19
1@
b111 "
b111 -
13
05
b0 ,
0/
b110 +
04
06
b11 L
b11 T
b11 \
b11 b
b1 c
b11 j
b11 r
0F
0G
0H
1N
1O
1P
00
b110 #
b110 &
b0 %
b0 (
b0 K
b0 S
b0 [
b0 a
b0 i
b0 q
b11000 t
#250
b110 "
b110 -
03
02
b0 )
0`
b0 c
b10 L
b10 T
b10 U
b10 \
b10 ]
b10 b
b10 j
b10 r
b1 %
b1 (
b1 K
b1 S
b1 [
b1 a
b1 i
b1 q
b11001 t
#260
0?
07
0>
18
b1 ,
1/
1;
0B
16
1<
0C
1R
b110 *
1Z
11
09
0@
b10 "
b10 -
03
b1 +
04
b1 L
b1 T
b100 U
b1 \
b100 ]
b1 b
b1 j
b1 r
10
b10 %
b10 (
b10 K
b10 S
b10 [
b10 a
b10 i
b10 q
b11010 t
#270
1!
1E
1?
0;
b11 ,
17
0B
0<
1>
0C
19
1@
b111 +
0R
b0 *
0Z
b1 "
b1 -
13
12
b0 U
b0 ]
b1 )
1`
b0 L
b0 T
b0 \
b0 b
b1000 c
b0 j
b0 r
b11 %
b11 (
b11 K
b11 S
b11 [
b11 a
b11 i
b11 q
b11011 t
#280
0;
1?
0<
1J
1R
b111 *
1Z
17
0B
1!
12
1>
0C
1E
18
b1 M
b1 U
b1 ]
b1 )
1`
11
19
1@
b0 "
b0 -
03
15
b11 ,
1/
b111 +
14
06
b11 L
b11 T
b11 \
b11 b
b1 c
b11 j
b11 r
1F
1G
1H
00
b111 #
b111 &
b0 %
b0 (
b0 K
b0 S
b0 [
b0 a
b0 i
b0 q
b11100 t
#290
1B
0!
1C
0E
0?
1;
07
1<
0>
08
b0 ,
0/
b111 "
b111 -
13
05
02
b0 )
0`
b0 c
b10 L
b10 M
b10 T
b10 U
b10 \
b10 ]
b10 b
b10 j
b10 r
b1 %
b1 (
b1 K
b1 S
b1 [
b1 a
b1 i
b1 q
b11101 t
#300
0;
0<
0B
0C
08
1J
1R
b111 *
1Z
01
09
0@
b1 "
b1 -
13
b0 ,
0/
b0 +
14
06
b1 L
b100 M
b1 T
b100 U
b1 \
b100 ]
b1 b
b1 j
b1 r
10
b10 %
b10 (
b10 K
b10 S
b10 [
b10 a
b10 i
b10 q
b11110 t
#310
1!
1E
1?
17
0B
04
16
1>
0C
0;
11
19
1@
0<
b111 +
18
b11 ,
1/
0J
0R
b0 *
0Z
b1 "
b1 -
13
05
12
b0 M
b0 U
b0 ]
b1 )
1`
b0 L
b0 T
b0 \
b0 b
b1000 c
b0 j
b0 r
b11 %
b11 (
b11 K
b11 S
b11 [
b11 a
b11 i
b11 q
b11111 t
#320
0;
0?
0<
07
0B
0!
12
0>
0C
0E
08
b1 )
1`
01
09
0@
b1 "
b1 -
13
05
b0 ,
0/
b0 +
04
06
b11 L
b11 T
b11 \
b11 b
b1 c
b11 j
b11 r
1I
1^
1_
0F
0G
0H
0N
0O
0P
0V
0W
0X
00
b1 $
b1 '
b0 #
b0 &
b0 %
b0 (
b0 K
b0 S
b0 [
b0 a
b0 i
b0 q
b100000 t
#330
b10 L
b10 T
b10 \
b10 b
b10 c
b10 j
b10 r
b1 %
b1 (
b1 K
b1 S
b1 [
b1 a
b1 i
b1 q
b100001 t
#340
1!
1E
1?
17
1>
0;
0B
18
12
16
0<
0C
b11 ,
1/
b1 )
1`
11
19
1@
b1 "
b1 -
13
05
b111 +
04
b1 L
b1 T
b1 \
b1 b
b100 c
b1 j
b1 r
10
b10 %
b10 (
b10 K
b10 S
b10 [
b10 a
b10 i
b10 q
b100010 t
#350
0B
1!
0C
1E
1?
0;
17
0<
1>
18
b0 "
b0 -
03
15
b11 ,
1/
14
06
01
b110 +
b1 *
1J
b0 L
b1000 M
b0 T
b0 \
b0 b
b1000 c
b0 j
b0 r
b11 %
b11 (
b11 K
b11 S
b11 [
b11 a
b11 i
b11 q
b100011 t
#360
0?
1;
07
0B
0!
18
12
1<
0>
0C
0E
b1 ,
1/
b1 *
1J
b1 )
1`
11
09
0@
b10 "
b10 -
03
15
b1 +
14
b11 L
b1 M
b11 T
b11 \
b11 b
b1 c
b11 j
b11 r
1F
1G
1H
00
b1 #
b1 &
b0 %
b0 (
b0 K
b0 S
b0 [
b0 a
b0 i
b0 q
b100100 t
#370
b10 L
b10 M
b10 T
b10 \
b10 b
b10 c
b10 j
b10 r
b1 %
b1 (
b1 K
b1 S
b1 [
b1 a
b1 i
b1 q
b100101 t
#380
1!
1E
18
1?
1/
0;
b11 ,
17
0B
12
0<
1>
0C
b1 *
1J
b1 )
1`
01
19
1@
b0 "
b0 -
03
15
b110 +
14
06
b1 L
b100 M
b1 T
b1 \
b1 b
b100 c
b1 j
b1 r
10
b10 %
b10 (
b10 K
b10 S
b10 [
b10 a
b10 i
b10 q
b100110 t
#390
b0 L
b1000 M
b0 T
b0 \
b0 b
b1000 c
b0 j
b0 r
b11 %
b11 (
b11 K
b11 S
b11 [
b11 a
b11 i
b11 q
b100111 t
#400
0?
1R
1;
07
0B
0!
08
12
1<
0>
0C
0E
b0 ,
0/
b10 *
0J
b1 U
b1 )
1`
01
19
0@
b11 "
b11 -
13
05
b10 +
04
b11 L
b0 M
b11 T
b11 \
b11 b
b1 c
b11 j
b11 r
0F
0G
0H
1N
1O
1P
00
b10 #
b10 &
b0 %
b0 (
b0 K
b0 S
b0 [
b0 a
b0 i
b0 q
b101000 t
#410
b10 L
b10 T
b10 U
b10 \
b10 b
b10 c
b10 j
b10 r
b1 %
b1 (
b1 K
b1 S
b1 [
b1 a
b1 i
b1 q
b101001 t
#420
0!
0E
0?
07
0>
1;
1B
18
12
16
1<
1C
b1 ,
1/
b10 *
1R
b1 )
1`
11
09
1@
b111 "
b111 -
13
05
b101 +
04
b1 L
b1 T
b100 U
b1 \
b1 b
b100 c
b1 j
b1 r
10
b10 %
b10 (
b10 K
b10 S
b10 [
b10 a
b10 i
b10 q
b101010 t
#430
0B
1!
0C
1E
1?
0;
17
18
0<
1>
b0 "
b0 -
03
15
b11 ,
1/
19
14
06
01
b110 +
0R
b1 *
1J
b0 U
b0 L
b1000 M
b0 T
b0 \
b0 b
b1000 c
b0 j
b0 r
b11 %
b11 (
b11 K
b11 S
b11 [
b11 a
b11 i
b11 q
b101011 t
#440
1?
1R
0;
17
1B
0!
18
12
0<
1>
1C
0E
b11 ,
1/
b11 *
1J
b1 U
b1 )
1`
11
19
0@
b100 "
b100 -
03
15
b11 +
14
b11 L
b1 M
b11 T
b11 \
b11 b
b1 c
b11 j
b11 r
1F
1G
1H
00
b11 #
b11 &
b0 %
b0 (
b0 K
b0 S
b0 [
b0 a
b0 i
b0 q
b101100 t
#450
b10 L
b10 M
b10 T
b10 U
b10 \
b10 b
b10 c
b10 j
b10 r
b1 %
b1 (
b1 K
b1 S
b1 [
b1 a
b1 i
b1 q
b101101 t
#460
18
0?
1/
1;
b1 ,
07
1B
0!
12
1<
0>
1C
0E
1J
b11 *
1R
b1 )
1`
01
09
1@
b110 "
b110 -
03
15
b100 +
14
06
b1 L
b100 M
b1 T
b100 U
b1 \
b1 b
b100 c
b1 j
b1 r
10
b10 %
b10 (
b10 K
b10 S
b10 [
b10 a
b10 i
b10 q
b101110 t
#470
0B
1!
0C
1E
1?
b0 "
b0 -
0;
b11 ,
17
0<
1>
19
b110 +
b1 *
0R
b0 U
b0 L
b1000 M
b0 T
b0 \
b0 b
b1000 c
b0 j
b0 r
b11 %
b11 (
b11 K
b11 S
b11 [
b11 a
b11 i
b11 q
b101111 t
#480
0?
1Z
0;
07
1B
0!
08
12
0<
0>
1C
0E
b0 ,
0/
b100 *
0J
b1 ]
b1 )
1`
01
09
1@
b101 "
b101 -
13
05
b100 +
04
b11 L
b0 M
b11 T
b11 \
b11 b
b1 c
b11 j
b11 r
0F
0G
0H
0N
0O
0P
1V
1W
1X
00
b100 #
b100 &
b0 %
b0 (
b0 K
b0 S
b0 [
b0 a
b0 i
b0 q
b110000 t
#490
b10 L
b10 T
b10 \
b10 ]
b10 b
b10 c
b10 j
b10 r
b1 %
b1 (
b1 K
b1 S
b1 [
b1 a
b1 i
b1 q
b110001 t
#500
1?
17
1>
0;
1B
18
12
16
0<
1C
b11 ,
1/
b100 *
1Z
b1 )
1`
11
19
0@
b101 "
b101 -
13
05
b11 +
04
b1 L
b1 T
b1 \
b100 ]
b1 b
b100 c
b1 j
b1 r
10
b10 %
b10 (
b10 K
b10 S
b10 [
b10 a
b10 i
b10 q
b110010 t
#510
1?
0;
17
0<
1>
0B
1!
18
0C
1E
b0 "
b0 -
03
15
b11 ,
1/
1@
14
06
01
b110 +
0Z
b1 *
1J
b0 ]
b0 L
b1000 M
b0 T
b0 \
b0 b
b1000 c
b0 j
b0 r
b11 %
b11 (
b11 K
b11 S
b11 [
b11 a
b11 i
b11 q
b110011 t
#520
0?
1Z
1;
07
1B
0!
18
12
1<
0>
1C
0E
b1 ,
1/
b101 *
1J
b1 ]
b1 )
1`
11
09
1@
b110 "
b110 -
03
15
b101 +
14
b11 L
b1 M
b11 T
b11 \
b11 b
b1 c
b11 j
b11 r
1F
1G
1H
00
b101 #
b101 &
b0 %
b0 (
b0 K
b0 S
b0 [
b0 a
b0 i
b0 q
b110100 t
#530
b10 L
b10 M
b10 T
b10 \
b10 ]
b10 b
b10 c
b10 j
b10 r
b1 %
b1 (
b1 K
b1 S
b1 [
b1 a
b1 i
b1 q
b110101 t
#540
0!
0E
18
1?
1/
0;
b11 ,
17
1B
12
0<
1>
1C
1J
b101 *
1Z
b1 )
1`
01
19
0@
b100 "
b100 -
03
15
b10 +
14
06
b1 L
b100 M
b1 T
b1 \
b100 ]
b1 b
b100 c
b1 j
b1 r
10
b10 %
b10 (
b10 K
b10 S
b10 [
b10 a
b10 i
b10 q
b110110 t
#550
b0 "
b0 -
0B
1!
0C
1E
1@
b110 +
b1 *
0Z
b0 ]
b0 L
b1000 M
b0 T
b0 \
b0 b
b1000 c
b0 j
b0 r
b11 %
b11 (
b11 K
b11 S
b11 [
b11 a
b11 i
b11 q
b110111 t
#560
0?
1R
1Z
1;
07
1B
0!
08
12
1<
0>
1C
0E
b0 ,
0/
b110 *
0J
b1 U
b1 ]
b1 )
1`
01
19
1@
b111 "
b111 -
13
05
b110 +
04
b11 L
b0 M
b11 T
b11 \
b11 b
b1 c
b11 j
b11 r
0F
0G
0H
1N
1O
1P
00
b110 #
b110 &
b0 %
b0 (
b0 K
b0 S
b0 [
b0 a
b0 i
b0 q
b111000 t
#570
b10 L
b10 T
b10 U
b10 \
b10 ]
b10 b
b10 c
b10 j
b10 r
b1 %
b1 (
b1 K
b1 S
b1 [
b1 a
b1 i
b1 q
b111001 t
#580
0?
07
0>
1;
0B
18
12
16
1<
0C
b1 ,
1/
1R
b110 *
1Z
b1 )
1`
11
09
0@
b11 "
b11 -
13
05
b1 +
04
b1 L
b1 T
b100 U
b1 \
b100 ]
b1 b
b100 c
b1 j
b1 r
10
b10 %
b10 (
b10 K
b10 S
b10 [
b10 a
b10 i
b10 q
b111010 t
#590
1!
1E
1?
0;
17
0B
18
0<
1>
0C
b0 "
b0 -
03
15
b11 ,
1/
19
1@
14
06
01
b110 +
0R
0Z
b1 *
1J
b0 U
b0 ]
b0 L
b1000 M
b0 T
b0 \
b0 b
b1000 c
b0 j
b0 r
b11 %
b11 (
b11 K
b11 S
b11 [
b11 a
b11 i
b11 q
b111011 t
#600
1?
1R
1Z
0;
17
0B
1!
18
12
0<
1>
0C
1E
b11 ,
1/
b111 *
1J
b1 U
b1 ]
b1 )
1`
11
19
1@
b0 "
b0 -
03
15
b111 +
14
b11 L
b1 M
b11 T
b11 \
b11 b
b1 c
b11 j
b11 r
1F
1G
1H
00
b111 #
b111 &
b0 %
b0 (
b0 K
b0 S
b0 [
b0 a
b0 i
b0 q
b111100 t
#610
b10 L
b10 M
b10 T
b10 U
b10 \
b10 ]
b10 b
b10 c
b10 j
b10 r
b1 %
b1 (
b1 K
b1 S
b1 [
b1 a
b1 i
b1 q
b111101 t
#620
18
0?
1/
1;
b1 ,
07
0B
0!
12
1<
0>
0C
0E
1J
1R
b111 *
1Z
b1 )
1`
01
09
0@
b10 "
b10 -
03
15
b0 +
14
06
b1 L
b100 M
b1 T
b100 U
b1 \
b100 ]
b1 b
b100 c
b1 j
b1 r
10
b10 %
b10 (
b10 K
b10 S
b10 [
b10 a
b10 i
b10 q
b111110 t
#630
1!
1E
1?
0;
b11 ,
17
b0 "
b0 -
0B
0<
1>
0C
19
1@
b110 +
0R
b1 *
0Z
b0 U
b0 ]
b0 L
b1000 M
b0 T
b0 \
b0 b
b1000 c
b0 j
b0 r
b11 %
b11 (
b11 K
b11 S
b11 [
b11 a
b11 i
b11 q
b111111 t
#640
0?
0;
07
0B
0!
08
12
0<
0>
0C
0E
b0 ,
0/
b0 *
0J
b1 )
1`
01
09
0@
b1 "
b1 -
13
05
b0 +
04
b11 L
b0 M
b11 T
b11 \
b11 b
b1 c
b11 j
b11 r
0I
1Q
0^
0_
1e
1f
0F
0G
0H
0N
0O
0P
0V
0W
0X
00
b10 $
b10 '
b0 #
b0 &
b0 %
b0 (
b0 K
b0 S
b0 [
b0 a
b0 i
b0 q
b1000000 t
#650
03
02
0`
b10 "
b10 -
1;
1:
b0 c
b10 )
1h
b10 L
b10 T
b10 \
b10 b
b10 j
b10 k
b10 r
b1 %
b1 (
b1 K
b1 S
b1 [
b1 a
b1 i
b1 q
b1000001 t
#660
1!
1E
1?
17
1>
18
b11 ,
1/
0B
1:
16
0<
0C
b10 )
1h
11
19
1@
b10 "
b10 -
03
b111 +
04
b1 L
b1 T
b1 \
b1 b
b1 j
b100 k
b1 r
10
b10 %
b10 (
b10 K
b10 S
b10 [
b10 a
b10 i
b10 q
b1000010 t
